sr.comp.scorer-1.8.0-py3.11-nspkg.pth
sr/comp/__init__.pyi
sr/comp/scorer/__init__.py
sr/comp/scorer/__main__.py
sr/comp/scorer/app.py
sr/comp/scorer/converter.py
sr/comp/scorer/py.typed
sr/comp/scorer/static/images/icon.png
sr/comp/scorer/static/images/logo.png
sr/comp/scorer/static/styles/dialogue.css
sr/comp/scorer/static/styles/main.css
sr/comp/scorer/static/styles/match-choice.css
sr/comp/scorer/static/styles/score-sheet.css
sr/comp/scorer/templates/404.html
sr/comp/scorer/templates/_base.html
sr/comp/scorer/templates/_update.html
sr/comp/scorer/templates/index.html
sr_comp_scorer-1.8.0.dist-info/licenses/AUTHORS.rst
sr_comp_scorer-1.8.0.dist-info/METADATA
sr_comp_scorer-1.8.0.dist-info/WHEEL
sr_comp_scorer-1.8.0.dist-info/namespace_packages.txt
sr_comp_scorer-1.8.0.dist-info/top_level.txt
sr_comp_scorer-1.8.0.dist-info/RECORD
