Metadata-Version: 2.4
Name: sr.comp.scorer
Version: 1.8.0
Summary: Student Robotics Competition Score Entry Application
Author: Student Robotics Competition Software SIG
Author-email: srobo-devel@googlegroups.com
Project-URL: Code, https://github.com/PeterJCLaw/srcomp-scorer
Project-URL: Issue tracker, https://github.com/PeterJCLaw/srcomp-scorer/issues
Classifier: Intended Audience :: Information Technology
Classifier: Operating System :: OS Independent
Classifier: Programming Language :: Python :: 3
Classifier: Programming Language :: Python :: 3.9
Classifier: Programming Language :: Python :: 3.10
Classifier: Programming Language :: Python :: 3.11
Classifier: Programming Language :: Python :: 3.12
Classifier: Programming Language :: Python :: 3 :: Only
Classifier: Topic :: Internet :: WWW/HTTP
Classifier: Topic :: Internet :: WWW/HTTP :: WSGI :: Application
Requires-Python: >=3.9
License-File: AUTHORS.rst
Requires-Dist: Flask<4,>=1.0
Requires-Dist: sr.comp<2,>=1.2
Provides-Extra: deploy
Requires-Dist: libproton; extra == "deploy"
Dynamic: author
Dynamic: author-email
Dynamic: classifier
Dynamic: description
Dynamic: license-file
Dynamic: project-url
Dynamic: provides-extra
Dynamic: requires-dist
Dynamic: requires-python
Dynamic: summary
